rolldet/__init__.py
rolldet/detector.py
rolldet/py.typed
rolldet/result.py
rolldet/target.py
rolldet-0.1.1.dist-info/LICENSE
rolldet-0.1.1.dist-info/WHEEL
rolldet-0.1.1.dist-info/METADATA
rolldet-0.1.1.dist-info/RECORD
