Metadata-Version: 2.1
Name: rolldet
Version: 0.1.1
Summary: Rickroll Detector
Author: ionite34
Author-email: dev@ionite.io
Requires-Python: >=3.8,<3.11
Classifier: Programming Language :: Python :: 3
Classifier: Programming Language :: Python :: 3.10
Classifier: Programming Language :: Python :: 3.8
Classifier: Programming Language :: Python :: 3.9
Requires-Dist: httpx (>=0.23.0,<0.24.0)
